{
    "title": "Transylvania Chronicles II - Son Of The Dragon",
    "source": "Vampire",
    "category": "Vampire",
    "tags": [
        "Transylvania",
        "Chronicles",
        "Dragon",
        "Vampire",
        "Camarilla",
        "Sabbat",
        "Anarch",
        "Traditions",
        "Umbra",
        "Kiths",
        "Clans",
        "Spheres"
    ],
    "description": "# File: Transylvania Chronicles II - Son Of The Dragon.txt",
    "filename": "Transylvania Chronicles II - Son Of The Dragon.txt",
    "relative_path": "Transylvania Chronicles II - Son Of The Dragon.txt"
}